plugs_filter/__init__.py
plugs_filter/decorators.py
plugs_filter/filters.py
plugs_filter/filtersets.py
plugs_filter/lookups.py
plugs_filter/runtests.py
plugs_filter/settings.py
plugs_filter/utils.py
plugs_filter-0.3.1.dist-info/AUTHORS.rst
plugs_filter-0.3.1.dist-info/LICENSE
plugs_filter-0.3.1.dist-info/METADATA
plugs_filter-0.3.1.dist-info/WHEEL
plugs_filter-0.3.1.dist-info/top_level.txt
plugs_filter-0.3.1.dist-info/RECORD
