Metadata-Version: 2.1
Name: plugs-filter
Version: 0.3.1
Summary: API auto filtering and ordering
Home-page: https://github.com/solocompt/plugs-filter
Author: Solo
Author-email: geral@solo.com.pt
License: MIT
Keywords: plugs-filter
Platform: UNKNOWN
Classifier: Development Status :: 3 - Alpha
Classifier: Framework :: Django :: 1.11
Classifier: Intended Audience :: Developers
Classifier: License :: OSI Approved :: MIT License
Classifier: Natural Language :: English
Classifier: Programming Language :: Python :: 3
Requires-Dist: django-filter (<3.0.0,>=2.1.0)
